README.md
setup.py
GameX/__init__.py
GameX/gameX.py
GameX.egg-info/PKG-INFO
GameX.egg-info/SOURCES.txt
GameX.egg-info/dependency_links.txt
GameX.egg-info/top_level.txt
GameX/data/fonts/My_font.ttf
GameX/data/images/gameX_icon.jpg