Metadata-Version: 2.1
Name: GameX
Version: 1.1.1
Summary: Welcome to GameX, a product developed using Pygame! It is more suitable for people have just switched from Scratch to Python. This lib is simple and easy to use.
